safepickling/__init__.py
safepickling-1.0.1.dist-info/WHEEL
safepickling-1.0.1.dist-info/METADATA
safepickling-1.0.1.dist-info/RECORD
