Metadata-Version: 2.1
Name: safepickling
Version: 1.0.1
Summary: SafePickling is a python library that allows you to sign and verify python pickles
Home-page: https://github.com/Wissotsky/SafePickling
License: MIT
Keywords: pickle,safe,sign,verify,security
Author: Wissotsky
Author-email: Wissotsky@protonmail.com
Requires-Python: >=3.9,<4.0
Classifier: License :: OSI Approved :: MIT License
Classifier: Programming Language :: Python :: 3
Classifier: Programming Language :: Python :: 3.10
Classifier: Programming Language :: Python :: 3.9
Project-URL: Repository, https://github.com/Wissotsky/SafePickling
